kptncook/__init__.py
kptncook/api.py
kptncook/config.py
kptncook/exporter_utils.py
kptncook/ingredient_groups.py
kptncook/mealie.py
kptncook/models.py
kptncook/paprika.py
kptncook/password_manager.py
kptncook/repositories.py
kptncook/tandoor.py
kptncook-0.0.26.dist-info/WHEEL
kptncook-0.0.26.dist-info/entry_points.txt
kptncook-0.0.26.dist-info/METADATA
kptncook-0.0.26.dist-info/RECORD
