Metadata-Version: 2.3
Name: kptncook
Version: 0.0.26
Summary: kptncook is a little command line utility to download new recipes.
Keywords: cooking,scraping,client,cli
Author: Jochen Wersdörfer
Author-email: Jochen Wersdörfer <jochen-kptncook@wersdoerfer.de>
Classifier: Programming Language :: Python :: 3
Classifier: Programming Language :: Python
Classifier: License :: OSI Approved :: MIT License
Classifier: Topic :: Internet
Classifier: Development Status :: 2 - Pre-Alpha
Classifier: Environment :: Web Environment
Classifier: License :: OSI Approved :: MIT License
Classifier: Programming Language :: Python :: 3 :: Only
Classifier: Programming Language :: Python :: 3.10
Classifier: Programming Language :: Python :: 3.11
Classifier: Programming Language :: Python :: 3.12
Requires-Dist: httpx>=0.22
Requires-Dist: feedparser>=6
Requires-Dist: rich>=11.1.0
Requires-Dist: pydantic>2
Requires-Dist: pydantic-settings
Requires-Dist: typer>=0.4
Requires-Dist: click
Requires-Dist: unidecode
Requires-Dist: jinja2
Requires-Python: >=3.10
Project-URL: Home, https://github.com/ephes/kptncook
